k8sclient/__init__.py
k8sclient/client/__init__.py
k8sclient/client/api_client.py
k8sclient/client/configuration.py
k8sclient/client/rest.py
k8sclient/client/apis/__init__.py
k8sclient/client/apis/apisbatchv_api.py
k8sclient/client/apis/apisextensionsvbeta_api.py
k8sclient/client/apis/apiv_api.py
k8sclient/client/models/__init__.py
k8sclient/client/models/integer.py
k8sclient/client/models/json_watch_event.py
k8sclient/client/models/unversioned_list_meta.py
k8sclient/client/models/unversioned_patch.py
k8sclient/client/models/unversioned_status.py
k8sclient/client/models/unversioned_status_cause.py
k8sclient/client/models/unversioned_status_details.py
k8sclient/client/models/v1_aws_elastic_block_store_volume_source.py
k8sclient/client/models/v1_azure_file_volume_source.py
k8sclient/client/models/v1_binding.py
k8sclient/client/models/v1_capabilities.py
k8sclient/client/models/v1_capability.py
k8sclient/client/models/v1_ceph_fs_volume_source.py
k8sclient/client/models/v1_cinder_volume_source.py
k8sclient/client/models/v1_component_condition.py
k8sclient/client/models/v1_component_status.py
k8sclient/client/models/v1_component_status_list.py
k8sclient/client/models/v1_config_map.py
k8sclient/client/models/v1_config_map_key_selector.py
k8sclient/client/models/v1_config_map_list.py
k8sclient/client/models/v1_config_map_volume_source.py
k8sclient/client/models/v1_container.py
k8sclient/client/models/v1_container_image.py
k8sclient/client/models/v1_container_port.py
k8sclient/client/models/v1_container_state.py
k8sclient/client/models/v1_container_state_running.py
k8sclient/client/models/v1_container_state_terminated.py
k8sclient/client/models/v1_container_state_waiting.py
k8sclient/client/models/v1_container_status.py
k8sclient/client/models/v1_daemon_endpoint.py
k8sclient/client/models/v1_delete_options.py
k8sclient/client/models/v1_downward_api_volume_file.py
k8sclient/client/models/v1_downward_api_volume_source.py
python_k8sclient-0.4.0.dist-info/DESCRIPTION.rst
python_k8sclient-0.4.0.dist-info/METADATA
python_k8sclient-0.4.0.dist-info/RECORD
python_k8sclient-0.4.0.dist-info/WHEEL
python_k8sclient-0.4.0.dist-info/metadata.json
python_k8sclient-0.4.0.dist-info/pbr.json
python_k8sclient-0.4.0.dist-info/top_level.txt
