Metadata-Version: 2.0
Name: python-k8sclient
Version: 0.4.0
Summary: This is Kubernetes API python client code. This code is generated by swagger-codegen. Kubernetes provide swagger-spec to generate client code for different versions. The specs live in Kubernetes repo.
Home-page: http://www.openstack.org/
Author: OpenStack
Author-email: openstack-dev@lists.openstack.org
License: UNKNOWN
Platform: UNKNOWN
Classifier: Environment :: OpenStack
Classifier: Intended Audience :: Information Technology
Classifier: Intended Audience :: System Administrators
Classifier: License :: OSI Approved :: Apache Software License
Classifier: Operating System :: POSIX :: Linux
Classifier: Programming Language :: Python
Classifier: Programming Language :: Python :: 2
Classifier: Programming Language :: Python :: 2.7
Classifier: Programming Language :: Python :: 3
Classifier: Programming Language :: Python :: 3.4
Classifier: Programming Language :: Python :: 3.5
Requires-Dist: pbr (>=1.6)
Requires-Dist: python-dateutil (>=2.4.2)
Requires-Dist: six (>=1.9.0)
Requires-Dist: urllib3 (>=1.8.3)
